README.txt
setup.py
Products/__init__.py
Products.CompositePage.egg-info/PKG-INFO
Products.CompositePage.egg-info/SOURCES.txt
Products.CompositePage.egg-info/dependency_links.txt
Products.CompositePage.egg-info/entry_points.txt
Products.CompositePage.egg-info/namespace_packages.txt
Products.CompositePage.egg-info/not-zip-safe
Products.CompositePage.egg-info/requires.txt
Products.CompositePage.egg-info/top_level.txt
Products/CompositePage/CHANGES.txt
Products/CompositePage/COPYRIGHT.txt
Products/CompositePage/LICENSE.txt
Products/CompositePage/README.txt
Products/CompositePage/__init__.py
Products/CompositePage/composite.py
Products/CompositePage/designuis.py
Products/CompositePage/element.py
Products/CompositePage/interfaces.py
Products/CompositePage/perm_names.py
Products/CompositePage/rawfile.py
Products/CompositePage/slot.py
Products/CompositePage/slotclass.py
Products/CompositePage/slotexpr.py
Products/CompositePage/tool.py
Products/CompositePage/utils.py
Products/CompositePage/version.txt
Products/CompositePage/cmf/bottom.pt
Products/CompositePage/cmf/cmf_edit.js
Products/CompositePage/cmf/header.pt
Products/CompositePage/common/bottom.pt
Products/CompositePage/common/changeTemplateForm.pt
Products/CompositePage/common/edit.js
Products/CompositePage/common/editstyles.css
Products/CompositePage/common/element.gif
Products/CompositePage/common/header.pt
Products/CompositePage/common/pdlib.js
Products/CompositePage/common/pdstyles.css
Products/CompositePage/common/target.gif
Products/CompositePage/common/target_active.gif
Products/CompositePage/common/target_hover.gif
Products/CompositePage/manual/add.gif
Products/CompositePage/manual/add_rollover.gif
Products/CompositePage/manual/body.pt
Products/CompositePage/manual/bottom.pt
Products/CompositePage/manual/copy.gif
Products/CompositePage/manual/copy_rollover.gif
Products/CompositePage/manual/cut.gif
Products/CompositePage/manual/cut_rollover.gif
Products/CompositePage/manual/header.pt
Products/CompositePage/manual/manual.js
Products/CompositePage/manual/manual_styles.css
Products/CompositePage/manual/paste.gif
Products/CompositePage/manual/paste_rollover.gif
Products/CompositePage/manual/remove.gif
Products/CompositePage/manual/remove_rollover.gif
Products/CompositePage/tests/__init__.py
Products/CompositePage/tests/test_composite.py
Products/CompositePage/tests/test_tool.py
