Metadata-Version: 1.0
Name: Products.CompositePage
Version: 1.1
Summary: CompositePage product
Home-page: http://pypi.python.org/pypi/Products.CompositePage
Author: Shane Hathaway
Author-email: shane@hathawaymix.org
License: ZPL 2.1 (http://www.zope.org/Resources/License/ZPL-2.1)
Keywords: web application server zope zope2 cmf plone
Platform: UNKNOWN
Classifier: Development Status :: 5 - Production/Stable
Classifier: Framework :: Plone
Classifier: Framework :: Zope2
Classifier: Intended Audience :: Developers
Classifier: License :: OSI Approved :: Zope Public License
Classifier: Programming Language :: Python
Classifier: Topic :: Software Development
